poetry_plugin_ignore_build_script/__init__.py
poetry_plugin_ignore_build_script/plugin.py
poetry_plugin_ignore_build_script-0.1.0.dist-info/LICENSE
poetry_plugin_ignore_build_script-0.1.0.dist-info/METADATA
poetry_plugin_ignore_build_script-0.1.0.dist-info/WHEEL
poetry_plugin_ignore_build_script-0.1.0.dist-info/entry_points.txt
poetry_plugin_ignore_build_script-0.1.0.dist-info/RECORD
