Metadata-Version: 2.1
Name: poetry-plugin-ignore-build-script
Version: 0.1.0
Summary: Poetry plugin that adds support for building non platform wheels by ignoring build scripts.
Home-page: https://github.com/bsdz/poetry-plugin-ignore-build-script
License: MIT
Author: Blair Azzopardi
Author-email: blairuk@gmail.com
Requires-Python: >=3.8,<4.0
Classifier: License :: OSI Approved :: MIT License
Classifier: Programming Language :: Python :: 3
Classifier: Programming Language :: Python :: 3.8
Classifier: Programming Language :: Python :: 3.9
Classifier: Programming Language :: Python :: 3.10
Classifier: Programming Language :: Python :: 3.11
Requires-Dist: poetry (>=1.2,<2.0)
Project-URL: Repository, https://github.com/bsdz/poetry-plugin-ignore-build-script
